clickflow_sync/__init__.py
clickflow_sync/engine.py
clickflow_sync/models.py
clickflow_sync/slack_plugin.py
clickflow_sync/state_provider.py
clickflow_sync-1.3.3.dist-info/licenses/LICENSE
clickflow_sync-1.3.3.dist-info/METADATA
clickflow_sync-1.3.3.dist-info/WHEEL
clickflow_sync-1.3.3.dist-info/top_level.txt
clickflow_sync-1.3.3.dist-info/RECORD
