Metadata-Version: 2.4
Name: ClickFlow-Sync
Version: 1.3.3
Summary: Professional ClickUp task automation with state sync.
Author: Jenil Mistry
License-File: LICENSE
Requires-Dist: flask
Requires-Dist: requests
Requires-Dist: python-dotenv
Dynamic: license-file
